file_flows/__init__.py
file_flows/core.py
file_flows/extensions.py
file_flows/s3.py
file_flows-0.1.6.dist-info/METADATA
file_flows-0.1.6.dist-info/WHEEL
file_flows-0.1.6.dist-info/top_level.txt
file_flows-0.1.6.dist-info/RECORD
