Metadata-Version: 2.1
Name: file-flows
Version: 0.1.6
Summary: A single high-level file operations API for both object stores and local file system.
Author-email: Dan Kelleher <kelleherjdan@gmail.com>
License: MIT
Classifier: Programming Language :: Python
Classifier: Programming Language :: Python :: 3
Classifier: Topic :: Software Development
Classifier: Topic :: Software Development :: Libraries
Classifier: Topic :: Software Development :: Libraries :: Python Modules
Requires-Dist: tqdm
Requires-Dist: s3fs[boto3]
Requires-Dist: pydantic >=2.0.0
Requires-Dist: pydantic-settings
Provides-Extra: dataframes
Requires-Dist: polars[all] ; extra == 'dataframes'
Requires-Dist: pyarrow ; extra == 'dataframes'
Provides-Extra: dev
Requires-Dist: black ; extra == 'dev'
Requires-Dist: pytest ; extra == 'dev'
